platops/__args__.py
platops/__files__.py
platops/__help__.py
platops/__main__.py
platops/__requests__.py
platops/__responses__.py
platops/agent.py
platops/list.py
platops/server.py
platops-0.0.4.dist-info/METADATA
platops-0.0.4.dist-info/WHEEL
platops-0.0.4.dist-info/top_level.txt
platops-0.0.4.dist-info/RECORD
