Metadata-Version: 2.1
Name: platops
Version: 0.0.4
Summary: PlatOps CLI
Home-page: https://platops.com
Author: Skrypnyk Kostiantyn
Author-email: skrypnyk.kostiantyn@gmail.com
License: UNKNOWN
Platform: UNKNOWN
Classifier: Programming Language :: Python :: 3
Classifier: License :: OSI Approved :: MIT License
Classifier: Operating System :: Unix
